sql2netx/__init__.py
sql2netx/base.py
sql2netx-0.0.2.dist-info/LICENSE
sql2netx-0.0.2.dist-info/METADATA
sql2netx-0.0.2.dist-info/WHEEL
sql2netx-0.0.2.dist-info/top_level.txt
sql2netx-0.0.2.dist-info/RECORD
