Metadata-Version: 2.1
Name: sql2netx
Version: 0.0.2
Summary: Converts a SQL query to a networkx graph.
Author-email: Galen Seilis <galen.seilis@seilis.ca>
Project-URL: Homepage, https://github.com/galenseilis/sql2netx
Project-URL: Bug Tracker, https://github.com/galenseilis/sql2netx/issues
Classifier: Programming Language :: Python :: 3
Classifier: License :: OSI Approved :: MIT License
Classifier: Operating System :: OS Independent
Requires-Python: >=3.7
License-File: LICENSE
